avro_dbo/__init__.py
avro_dbo/decorator.py
avro_dbo/import.py
avro_dbo/py.typed
avro_dbo-1.0.0.dist-info/METADATA
avro_dbo-1.0.0.dist-info/WHEEL
avro_dbo-1.0.0.dist-info/RECORD
